{
  "participant_id": "004",
  "condition_order": "BABA",
  "start_time": "2025-06-24T23:18:05.779873",
  "blocks_completed": [
    {
      "block_number": 1,
      "condition": "flashcard",
      "completion_time": "2025-06-24T23:23:25.807863",
      "duration_minutes": 5
    },
    {
      "block_number": 2,
      "condition": "conversational",
      "completion_time": "2025-06-24T23:29:02.624248",
      "duration_minutes": 5
    },
    {
      "block_number": 3,
      "condition": "flashcard",
      "completion_time": "2025-06-24T23:42:43.583747",
      "duration_minutes": 5
    },
    {
      "block_number": 4,
      "condition": "conversational",
      "completion_time": "2025-06-24T23:51:16.621163",
      "duration_minutes": 5
    }
  ],
  "rimms_scores": {
    "flashcard": {
      "completed": true,
      "completion_time": "2025-06-24T23:45:31.146333"
    },
    "conversational": {
      "completed": true,
      "completion_time": "2025-06-25T00:00:08.168490"
    }
  },
  "vocabulary_sets": {},
  "session_complete": true,
  "completion_time": "2025-06-25T00:00:08.169326",
  "posttest": {
    "scheduled_time": "2025-06-26T00:00:08.169420",
    "generated": true
  }
}